{"repo": {"name": {"en-US": "litetex's Test Repo"}, "description": {"en-US": "This is a F-Droid repository used for testing.  Provided using a static site hosting service like GitHub Pages."}, "icon": {"en-US": {"name": "/icons/icon.png", "sha256": "a8502800c1668649d3236fa8ed9b7c8c8c7dfb26da4fbb16431f14d92e54e00c", "size": 103780}}, "address": "https://litetex.github.io/fdroid-pages/fdroid/repo", "mirrors": [{"isPrimary": true, "url": "https://litetex.github.io/fdroid-pages/fdroid/repo"}, {"url": "https://litetex.codeberg.page/fdroid-pages/fdroid/repo"}], "timestamp": 1740795196000, "categories": {"Internet": {"name": {"en-US": "Internet"}}, "Multimedia": {"name": {"en-US": "Multimedia"}}}}, "packages": {"org.schabi.newpipe.nightly": {"metadata": {"added": 1739754939000, "categories": ["Internet", "Multimedia"], "changelog": "https://github.com/TeamNewPipe/NewPipe-nightly/releases", "issueTracker": "https://github.com/TeamNewPipe/NewPipe/issues", "lastUpdated": 1740791861000, "license": "GPL-3.0-or-later", "sourceCode": "https://github.com/TeamNewPipe/NewPipe", "translation": "https://hosted.weblate.org/projects/newpipe/", "webSite": "https://newpipe.net", "featureGraphic": {"en-US": {"name": "/org.schabi.newpipe.nightly/en-US/featureGraphic_Qq9SZzTnSL4S6Rw9e2LkFe1zyLTO8elMFrDinLyXUPY=.png", "sha256": "42af526734e748be12e91c3d7b62e415ed73c8b4cef1e94c16b0e29cbc9750f6", "size": 18490}}, "authorEmail": "team@newpipe.net", "authorName": "Team NewPipe", "name": {"en-US": "NewPipe nightly"}, "summary": {"en-US": "A free lightweight YouTube frontend for Android (Nightly)"}, "description": {"en-US": "This is a preview version of NewPipe with the latest cutting edge changes from the development branch"}, "icon": {"en-US": {"name": "/org.schabi.newpipe.nightly/en-US/icon_UZT70o1xbRQUoaYZsV6csIZ6UBTfkV_oVU5J-9QL_Ys=.png", "sha256": "5194fbd28d716d1414a1a619b15e9cb0867a5014df915fe8554e49fbd40bfd8b", "size": 18022}}, "preferredSigner": "52cdaa5f53ad0dea7cfcc88f7ae8865c488591b4ec7724cfc5490ccf9e189b6f"}, "versions": {"df01c5c8501bccb58aa0a964ea0642a0beb5131dfa1ec492ee978c02c4b99009": {"added": 1740791861000, "file": {"name": "/NewPipe_nightly-1028.apk", "sha256": "df01c5c8501bccb58aa0a964ea0642a0beb5131dfa1ec492ee978c02c4b99009", "size": 11960516}, "manifest": {"versionName": "0.27.6-1028-202503010114", "versionCode": 1028, "usesSdk": {"minSdkVersion": 21, "targetSdkVersion": 33}, "signer": {"sha256": ["52cdaa5f53ad0dea7cfcc88f7ae8865c488591b4ec7724cfc5490ccf9e189b6f"]}, "usesPermission": [{"name": "android.permission.INTERNET"}, {"name": "android.permission.WAKE_LOCK"}, {"name": "android.permission.ACCESS_NETWORK_STATE"}, {"name": "android.permission.WRITE_EXTERNAL_STORAGE"}, {"name": "android.permission.SYSTEM_ALERT_WINDOW"}, {"name": "android.permission.FOREGROUND_SERVICE"}, {"name": "android.permission.POST_NOTIFICATIONS"}, {"name": "android.permission.RECEIVE_BOOT_COMPLETED"}, {"name": "org.schabi.newpipe.nightly.DYNAMIC_RECEIVER_NOT_EXPORTED_PERMISSION"}, {"name": "android.permission.READ_EXTERNAL_STORAGE"}]}, "antiFeatures": {"NonFreeNet": {"en-US": "Depends on Youtube for videos."}}}, "61816b91a36eb85db407117701e8c0a51c8ceb2870c4065e28743b7432865c01": {"added": 1740186578000, "file": {"name": "/NewPipe_nightly-1027.apk", "sha256": "61816b91a36eb85db407117701e8c0a51c8ceb2870c4065e28743b7432865c01", "size": 11960516}, "manifest": {"versionName": "0.27.6-1027-202502220106", "versionCode": 1027, "usesSdk": {"minSdkVersion": 21, "targetSdkVersion": 33}, "signer": {"sha256": ["52cdaa5f53ad0dea7cfcc88f7ae8865c488591b4ec7724cfc5490ccf9e189b6f"]}, "usesPermission": [{"name": "android.permission.INTERNET"}, {"name": "android.permission.WAKE_LOCK"}, {"name": "android.permission.ACCESS_NETWORK_STATE"}, {"name": "android.permission.WRITE_EXTERNAL_STORAGE"}, {"name": "android.permission.SYSTEM_ALERT_WINDOW"}, {"name": "android.permission.FOREGROUND_SERVICE"}, {"name": "android.permission.POST_NOTIFICATIONS"}, {"name": "android.permission.RECEIVE_BOOT_COMPLETED"}, {"name": "org.schabi.newpipe.nightly.DYNAMIC_RECEIVER_NOT_EXPORTED_PERMISSION"}, {"name": "android.permission.READ_EXTERNAL_STORAGE"}]}, "antiFeatures": {"NonFreeNet": {"en-US": "Depends on Youtube for videos."}}}, "2e7b6dc8bae626b3f63cfb6e2f69d1c45be1d0c98307f5d050fb8eb68946b6b7": {"added": 1739754939000, "file": {"name": "/NewPipe_nightly-1026.apk", "sha256": "2e7b6dc8bae626b3f63cfb6e2f69d1c45be1d0c98307f5d050fb8eb68946b6b7", "size": 11960516}, "manifest": {"versionName": "0.27.6-1026-202502170110", "versionCode": 1026, "usesSdk": {"minSdkVersion": 21, "targetSdkVersion": 33}, "signer": {"sha256": ["52cdaa5f53ad0dea7cfcc88f7ae8865c488591b4ec7724cfc5490ccf9e189b6f"]}, "usesPermission": [{"name": "android.permission.INTERNET"}, {"name": "android.permission.WAKE_LOCK"}, {"name": "android.permission.ACCESS_NETWORK_STATE"}, {"name": "android.permission.WRITE_EXTERNAL_STORAGE"}, {"name": "android.permission.SYSTEM_ALERT_WINDOW"}, {"name": "android.permission.FOREGROUND_SERVICE"}, {"name": "android.permission.POST_NOTIFICATIONS"}, {"name": "android.permission.RECEIVE_BOOT_COMPLETED"}, {"name": "org.schabi.newpipe.nightly.DYNAMIC_RECEIVER_NOT_EXPORTED_PERMISSION"}, {"name": "android.permission.READ_EXTERNAL_STORAGE"}]}, "antiFeatures": {"NonFreeNet": {"en-US": "Depends on Youtube for videos."}}}}}, "org.schabi.newpipe.refactor.nightly": {"metadata": {"added": 1738513077000, "categories": ["Internet", "Multimedia"], "changelog": "https://github.com/TeamNewPipe/NewPipe-refactor-nightly/releases", "issueTracker": "https://github.com/TeamNewPipe/NewPipe/issues", "lastUpdated": 1740619766000, "license": "GPL-3.0-or-later", "sourceCode": "https://github.com/TeamNewPipe/NewPipe/tree/refactor", "translation": "https://hosted.weblate.org/projects/newpipe/", "webSite": "https://newpipe.net", "featureGraphic": {"en-US": {"name": "/org.schabi.newpipe.refactor.nightly/en-US/featureGraphic_Qq9SZzTnSL4S6Rw9e2LkFe1zyLTO8elMFrDinLyXUPY=.png", "sha256": "42af526734e748be12e91c3d7b62e415ed73c8b4cef1e94c16b0e29cbc9750f6", "size": 18490}}, "authorEmail": "team@newpipe.net", "authorName": "Team NewPipe", "name": {"en-US": "NewPipe refactor.nightly"}, "summary": {"en-US": "A free lightweight YouTube frontend for Android (Refactoring Nightly)"}, "description": {"en-US": "This is a preview version of NewPipe with the latest cutting edge changes from the refactor branch"}, "icon": {"en-US": {"name": "/org.schabi.newpipe.refactor.nightly/en-US/icon_tqrpVkQLWCAZ9Unoncm1uNjGGtaqngztPQ4YX6BaTfI=.png", "sha256": "b6aae956440b582019f549e89dc9b5b8d8c61ad6aa9e0ced3d0e185fa05a4df2", "size": 20265}}, "preferredSigner": "4b12cb8c7a4448c662496dcf8b614f277c2013f1f0e0edeb9cd267cb360153b9"}, "versions": {"4bc4eb579b3ab2a22a3c2e0e5ad53a010791cc03796d2f05ba2188a3c6a3ac6d": {"added": 1740619766000, "file": {"name": "/NewPipe_nightly-12.apk", "sha256": "4bc4eb579b3ab2a22a3c2e0e5ad53a010791cc03796d2f05ba2188a3c6a3ac6d", "size": 14381142}, "manifest": {"nativecode": ["arm64-v8a", "armeabi-v7a", "x86", "x86_64"], "versionName": "0.27.6-12-202502270123", "versionCode": 12, "usesSdk": {"minSdkVersion": 21, "targetSdkVersion": 33}, "signer": {"sha256": ["4b12cb8c7a4448c662496dcf8b614f277c2013f1f0e0edeb9cd267cb360153b9"]}, "usesPermission": [{"name": "android.permission.INTERNET"}, {"name": "android.permission.WAKE_LOCK"}, {"name": "android.permission.ACCESS_NETWORK_STATE"}, {"name": "android.permission.WRITE_EXTERNAL_STORAGE"}, {"name": "android.permission.SYSTEM_ALERT_WINDOW"}, {"name": "android.permission.FOREGROUND_SERVICE"}, {"name": "android.permission.POST_NOTIFICATIONS"}, {"name": "android.permission.RECEIVE_BOOT_COMPLETED"}, {"name": "org.schabi.newpipe.refactor.nightly.DYNAMIC_RECEIVER_NOT_EXPORTED_PERMISSION"}, {"name": "android.permission.READ_EXTERNAL_STORAGE"}]}, "antiFeatures": {"NonFreeNet": {"en-US": "Depends on Youtube for videos."}}}, "7413b8141e797e49e35828c333d154664c84b12f25b2c76c57c36849adcaf7d2": {"added": 1738765568000, "file": {"name": "/NewPipe_nightly-11.apk", "sha256": "7413b8141e797e49e35828c333d154664c84b12f25b2c76c57c36849adcaf7d2", "size": 14381142}, "manifest": {"nativecode": ["arm64-v8a", "armeabi-v7a", "x86", "x86_64"], "versionName": "0.27.6-11-202502051420", "versionCode": 11, "usesSdk": {"minSdkVersion": 21, "targetSdkVersion": 33}, "signer": {"sha256": ["4b12cb8c7a4448c662496dcf8b614f277c2013f1f0e0edeb9cd267cb360153b9"]}, "usesPermission": [{"name": "android.permission.INTERNET"}, {"name": "android.permission.WAKE_LOCK"}, {"name": "android.permission.ACCESS_NETWORK_STATE"}, {"name": "android.permission.WRITE_EXTERNAL_STORAGE"}, {"name": "android.permission.SYSTEM_ALERT_WINDOW"}, {"name": "android.permission.FOREGROUND_SERVICE"}, {"name": "android.permission.POST_NOTIFICATIONS"}, {"name": "android.permission.RECEIVE_BOOT_COMPLETED"}, {"name": "org.schabi.newpipe.refactor.nightly.DYNAMIC_RECEIVER_NOT_EXPORTED_PERMISSION"}, {"name": "android.permission.READ_EXTERNAL_STORAGE"}]}, "antiFeatures": {"NonFreeNet": {"en-US": "Depends on Youtube for videos."}}}, "fb7ca0745a2a072f09d6fdbddb6fd4a714af720783b52963d5de3bd3d15a8832": {"added": 1738513077000, "file": {"name": "/NewPipe_nightly-10.apk", "sha256": "fb7ca0745a2a072f09d6fdbddb6fd4a714af720783b52963d5de3bd3d15a8832", "size": 14262151}, "manifest": {"nativecode": ["arm64-v8a", "armeabi-v7a", "x86", "x86_64"], "versionName": "0.27.5-10-202502021612", "versionCode": 10, "usesSdk": {"minSdkVersion": 21, "targetSdkVersion": 33}, "signer": {"sha256": ["4b12cb8c7a4448c662496dcf8b614f277c2013f1f0e0edeb9cd267cb360153b9"]}, "usesPermission": [{"name": "android.permission.INTERNET"}, {"name": "android.permission.WAKE_LOCK"}, {"name": "android.permission.ACCESS_NETWORK_STATE"}, {"name": "android.permission.WRITE_EXTERNAL_STORAGE"}, {"name": "android.permission.SYSTEM_ALERT_WINDOW"}, {"name": "android.permission.FOREGROUND_SERVICE"}, {"name": "android.permission.POST_NOTIFICATIONS"}, {"name": "android.permission.RECEIVE_BOOT_COMPLETED"}, {"name": "org.schabi.newpipe.refactor.nightly.DYNAMIC_RECEIVER_NOT_EXPORTED_PERMISSION"}, {"name": "android.permission.READ_EXTERNAL_STORAGE"}]}, "antiFeatures": {"NonFreeNet": {"en-US": "Depends on Youtube for videos."}}}}}}}